Metadata-Version: 1.1
Name: nsim
Version: 0.1.14
Summary: Simulate systems from ODEs or SDEs, analyze timeseries.
Home-page: http://github.com/mattja/nsim/
Author: Matthew J. Aburn
Author-email: mattja6@gmail.com
License: GPLv3+
Keywords: simulation,ODE,SDE,SODE,time series
Platform: any
Classifier: Programming Language :: Python
Classifier: Development Status :: 2 - Pre-Alpha
Classifier: Intended Audience :: Science/Research
Classifier: License :: OSI Approved :: GNU General Public License (GPL)
Classifier: Operating System :: OS Independent
Classifier: Topic :: Scientific/Engineering :: Physics
Classifier: Topic :: System :: Distributed Computing
